{
	"name": "errormessage",
	"properties": {
		"activities": [
			{
				"name": "Set variable1",
				"type": "SetVariable",
				"dependsOn": [],
				"userProperties": [],
				"typeProperties": {
					"variableName": "varc",
					"value": "mani"
				}
			},
			{
				"name": "Set variable2",
				"type": "SetVariable",
				"dependsOn": [],
				"userProperties": [],
				"typeProperties": {
					"variableName": "varc",
					"value": "mani"
				}
			},
			{
				"name": "Set variable3",
				"type": "SetVariable",
				"dependsOn": [],
				"userProperties": [],
				"typeProperties": {
					"variableName": "varc",
					"value": ""
				}
			},
			{
				"name": "Wait1",
				"type": "Wait",
				"dependsOn": [
					{
						"activity": "Set variable1",
						"dependencyConditions": [
							"Succeeded"
						]
					},
					{
						"activity": "Set variable2",
						"dependencyConditions": [
							"Succeeded"
						]
					},
					{
						"activity": "Set variable3",
						"dependencyConditions": [
							"Succeeded"
						]
					}
				],
				"userProperties": [],
				"typeProperties": {
					"waitTimeInSeconds": 1
				}
			},
			{
				"name": "Set variable4",
				"type": "SetVariable",
				"dependsOn": [
					{
						"activity": "Wait1",
						"dependencyConditions": [
							"Succeeded"
						]
					}
				],
				"userProperties": []
			}
		],
		"variables": {
			"varc": {
				"type": "String"
			}
		},
		"annotations": []
	}
}